monobankua/__init__.py
monobankua/client.py
monobankua/sign.py
monobankua-0.4.5.dist-info/licenses/LICENSE
monobankua-0.4.5.dist-info/METADATA
monobankua-0.4.5.dist-info/WHEEL
monobankua-0.4.5.dist-info/top_level.txt
monobankua-0.4.5.dist-info/RECORD
