Metadata-Version: 2.4
Name: monobankua
Version: 0.4.5
Summary: Monobank.ua API client
Home-page: https://github.com/inbalboa/python-monobankua
Author: Serhiy Shliapuhin
Author-email: shlyapugin@gmail.com
License: GPLv3
Classifier: Programming Language :: Python :: 3
Classifier: Programming Language :: Python :: 3.10
Classifier: Programming Language :: Python :: 3 :: Only
Classifier: License :: OSI Approved
Classifier: License :: OSI Approved :: GNU General Public License v3 (GPLv3)
Classifier: Operating System :: OS Independent
Requires-Python: >=3.10,<4.0
License-File: LICENSE
Requires-Dist: requests<3.0,>=2.21
Requires-Dist: ecdsa>=0.13.2
Dynamic: author
Dynamic: author-email
Dynamic: classifier
Dynamic: description
Dynamic: description-content-type
Dynamic: home-page
Dynamic: license
Dynamic: license-file
Dynamic: requires-dist
Dynamic: requires-python
Dynamic: summary
